scrapydart/MysqlOrm_information.py
scrapydart/VERSION
scrapydart/__init__.py
scrapydart/_deprecate.py
scrapydart/app.py
scrapydart/auth.py
scrapydart/config.py
scrapydart/default_scrapyd.conf
scrapydart/eggstorage.py
scrapydart/eggutils.py
scrapydart/environ.py
scrapydart/interfaces.py
scrapydart/launcher.py
scrapydart/model_news_infomation.py
scrapydart/poller.py
scrapydart/runner.py
scrapydart/runtime_monitor.py
scrapydart/scheduler.py
scrapydart/script.py
scrapydart/spiderqueue.py
scrapydart/sqlite.py
scrapydart/txapp.py
scrapydart/utils.py
scrapydart/webservice.py
scrapydart/website.py
scrapydart/websource.py
scrapydart/webtools.py
scrapydart/scripts/__init__.py
scrapydart/scripts/scrapyd_run.py
scrapydart/template/documents.html
scrapydart/template/feature.html
scrapydart/template/footers.html
scrapydart/template/header.html
scrapydart/template/index.html
scrapydart/template/jobs.html
scrapydart/template/css/reset.css
scrapydart/template/css/style.css
scrapydart/template/img/cd-icon-arrow.svg
scrapydart/template/js/jquery-2.1.4.js
scrapydart/template/js/main.js
scrapydart/template/js/modern.js
scrapydart/template/js/velocity.min.js
scrapydartx/Time_Method.py
scrapydartx/VERSION
scrapydartx/__init__.py
scrapydartx/_deprecate.py
scrapydartx/app.py
scrapydartx/auth.py
scrapydartx/config.py
scrapydartx/default_scrapyd.conf
scrapydartx/eggstorage.py
scrapydartx/eggutils.py
scrapydartx/environ.py
scrapydartx/global_values.py
scrapydartx/interfaces.py
scrapydartx/launcher.py
scrapydartx/mysql_models.py
scrapydartx/mysql_orm.py
scrapydartx/mysql_runtime_monitor.py
scrapydartx/mysql_time_scheduling.py
scrapydartx/poller.py
scrapydartx/runner.py
scrapydartx/scheduler.py
scrapydartx/scrapydart_extend.py
scrapydartx/script.py
scrapydartx/spiderqueue.py
scrapydartx/sqlite.py
scrapydartx/sqlite_model.py
scrapydartx/sqlite_orm.py
scrapydartx/sqlite_runtime_monitor.py
scrapydartx/sqlite_time_scheduling.py
scrapydartx/txapp.py
scrapydartx/utils.py
scrapydartx/webservice.py
scrapydartx-1.3.2.dist-info/LICENSE
scrapydartx-1.3.2.dist-info/METADATA
scrapydartx-1.3.2.dist-info/WHEEL
scrapydartx-1.3.2.dist-info/entry_points.txt
scrapydartx-1.3.2.dist-info/top_level.txt
scrapydartx-1.3.2.dist-info/RECORD
