Metadata-Version: 2.1
Name: scrapydartx
Version: 1.3.2
Summary: a extension from ScrapydArt
Home-page: https://github.com/GuardianGH/scrapydartx
Author: Scrapy developers
Author-email: zhling2012@live.com
Maintainer: Scrapy developers
Maintainer-email: info@scrapy.org
License: UNKNOWN
Platform: UNKNOWN
Classifier: Programming Language :: Python
Classifier: Programming Language :: Python :: 3
Classifier: Programming Language :: Python :: 3.4
Classifier: Programming Language :: Python :: 3.5
Classifier: Programming Language :: Python :: 3.6
Classifier: License :: OSI Approved :: BSD License
Classifier: Operating System :: OS Independent
Classifier: Development Status :: 5 - Production/Stable
Classifier: Environment :: Console
Classifier: Environment :: No Input/Output (Daemon)
Classifier: Topic :: Internet :: WWW/HTTP
Requires-Dist: attrs (==19.3.0)
Requires-Dist: Automat (==0.8.0)
Requires-Dist: bleach (==3.1.0)
Requires-Dist: certifi (==2019.11.28)
Requires-Dist: cffi (==1.13.2)
Requires-Dist: chardet (==3.0.4)
Requires-Dist: constantly (==15.1.0)
Requires-Dist: cryptography (==2.8)
Requires-Dist: cssselect (==1.1.0)
Requires-Dist: docutils (==0.15.2)
Requires-Dist: enum-compat (==0.0.3)
Requires-Dist: hyperlink (==19.0.0)
Requires-Dist: idna (==2.8)
Requires-Dist: importlib-metadata (==1.3.0)
Requires-Dist: incremental (==17.5.0)
Requires-Dist: jeepney (==0.4.1)
Requires-Dist: keyring (==20.0.0)
Requires-Dist: lxml (==4.4.2)
Requires-Dist: more-itertools (==8.0.2)
Requires-Dist: numpy (==1.17.4)
Requires-Dist: parsel (==1.5.2)
Requires-Dist: pkginfo (==1.5.0.1)
Requires-Dist: Protego (==0.1.16)
Requires-Dist: psutil (==5.6.7)
Requires-Dist: pyasn1 (==0.4.8)
Requires-Dist: pyasn1-modules (==0.2.7)
Requires-Dist: pycparser (==2.19)
Requires-Dist: PyDispatcher (==2.0.5)
Requires-Dist: Pygments (==2.5.2)
Requires-Dist: PyHamcrest (==1.9.0)
Requires-Dist: PyMySQL (==0.9.3)
Requires-Dist: pyOpenSSL (==19.1.0)
Requires-Dist: queuelib (==1.5.0)
Requires-Dist: readme-renderer (==24.0)
Requires-Dist: requests (==2.22.0)
Requires-Dist: requests-toolbelt (==0.9.1)
Requires-Dist: Scrapy (==1.8.0)
Requires-Dist: SecretStorage (==3.1.1)
Requires-Dist: service-identity (==18.1.0)
Requires-Dist: six (==1.13.0)
Requires-Dist: SQLAlchemy (==1.3.12)
Requires-Dist: tqdm (==4.40.2)
Requires-Dist: twine (==3.1.0)
Requires-Dist: Twisted (==18.9.0)
Requires-Dist: urllib3 (==1.25.7)
Requires-Dist: w3lib (==1.21.0)
Requires-Dist: webencodings (==0.5.1)
Requires-Dist: zipp (==0.6.0)
Requires-Dist: zope.interface (==4.7.1)
